bookmarker/__init__.py
bookmarker/__main__.py
bookmarker/cli/__init__.py
bookmarker/cli/base.py
bookmarker/cli/fetchers.py
bookmarker/cli/helpers.py
bookmarker/cli/init_config.py
bookmarker/cli/main.py
bookmarker/cli/summarizers.py
bookmarker/core/__init__.py
bookmarker/core/config.py
bookmarker/core/database.py
bookmarker/core/exceptions.py
bookmarker/core/fetchers.py
bookmarker/core/main.py
bookmarker/core/models.py
bookmarker/core/summarizers.py
bookmarker/services/__init__.py
bookmarker/services/base.py
bookmarker/services/fetchers.py
bookmarker/services/summarizers.py
bookmarker_ai-0.3.0.dist-info/METADATA
bookmarker_ai-0.3.0.dist-info/WHEEL
bookmarker_ai-0.3.0.dist-info/entry_points.txt
bookmarker_ai-0.3.0.dist-info/licenses/LICENSE
bookmarker_ai-0.3.0.dist-info/RECORD
