Metadata-Version: 2.4
Name: bookmarker-ai
Version: 0.3.0
Summary: A CLI tool to manage the online articles you want to read. Too much content and too little time? Bookmarker helps you pick what to read.
Project-URL: Homepage, https://github.com/kishanpatel789/bookmarker
Project-URL: Issues, https://github.com/kishanpatel789/bookmarker/issues
Author-email: Kishan Patel <kishanpatel789@gmail.com>
License-Expression: MIT
License-File: LICENSE
Requires-Python: >=3.13
Requires-Dist: pydantic-ai-slim[openai]>=1.0.10
Requires-Dist: python-decouple>=3.8
Requires-Dist: sqlmodel>=0.0.25
Requires-Dist: trafilatura>=2.0.0
Requires-Dist: typer>=0.19.2
